unyts/Empty.py
unyts/__init__.py
unyts/__main__.py
unyts/converter.py
unyts/database.py
unyts/dictionaries.py
unyts/errors.py
unyts/gui.py
unyts/network.py
unyts/operations.py
unyts/parameters.ini
unyts/parameters.py
unyts/searches.py
unyts/unit_class.py
unyts/unitary.py
unyts/unyts_icon.ico
unyts/helpers/__init__.py
unyts/helpers/caster.py
unyts/helpers/common_classes.py
unyts/helpers/is_number.py
unyts/helpers/is_unit.py
unyts/helpers/lambda_to_def.py
unyts/helpers/logger.py
unyts/helpers/multi_split.py
unyts/helpers/unit_string_tools.py
unyts/units/__init__.py
unyts/units/custom.py
unyts/units/data.py
unyts/units/date.py
unyts/units/def_conversions.py
unyts/units/def_prefixes.py
unyts/units/define.py
unyts/units/energy.py
unyts/units/force.py
unyts/units/geometry.py
unyts/units/mass.py
unyts/units/rates.py
unyts/units/ratios.py
unyts/units/temperature.py
unyts/units/time.py
unyts/units/unitless.py
unyts-0.9.15.dist-info/licenses/LICENSE
unyts-0.9.15.dist-info/METADATA
unyts-0.9.15.dist-info/WHEEL
unyts-0.9.15.dist-info/top_level.txt
unyts-0.9.15.dist-info/RECORD
