Metadata-Version: 2.4
Name: unyts
Version: 0.9.15
Summary: an unit converter based on graph network and classes to operate with units.
Author-email: Martin Carlos Araya <martinaraya@gmail.com>
License: MIT License
Project-URL: Homepage, https://github.com/ayaranitram/unyts
Project-URL: Bug Tracker, https://github.com/ayaranitram/unyts/issues
Classifier: Programming Language :: Python :: 3.7
Classifier: Programming Language :: Python :: 3.8
Classifier: Programming Language :: Python :: 3.9
Classifier: Programming Language :: Python :: 3.10
Classifier: Programming Language :: Python :: 3.11
Classifier: License :: OSI Approved :: MIT License
Classifier: Operating System :: OS Independent
Requires-Python: >=3.7
License-File: LICENSE
Requires-Dist: stringthings
Requires-Dist: cloudpickle
Dynamic: license-file
